basictools/TEM_utilities.py
basictools/__init__.py
basictools/_decorators.py
basictools/algebrautils.py
basictools/data_io.py
basictools/fitLatticePeaks.py
basictools/fitPeaks.py
basictools/image_filters.py
basictools/jsontools.py
basictools/metadata.py
basictools/plottingtools.py
basictools/processing.py
basictools/guitools/__init__.py
basictools/guitools/file_dialog.py
basictools/guitools/save_file_dialog.py
basictools/guitools/widgets.py
temmeta/TEM_utilities.py
temmeta/__init__.py
temmeta/_decorators.py
temmeta/algebrautils.py
temmeta/api.py
temmeta/data_io.py
temmeta/fitLatticePeaks.py
temmeta/fitPeaks.py
temmeta/image_filters.py
temmeta/jsontools.py
temmeta/metadata.py
temmeta/plottingtools.py
temmeta/processing.py
temmeta/dataio/__init__.py
temmeta/dataio/_veloxEMD.py
temmeta/datatypes/__init__.py
temmeta/datatypes/_data1D.py
temmeta/datatypes/_data2D.py
temmeta/datatypes/_data3D.py
temmeta/datatypes/_dataimage.py
temmeta/datatypes/_dataspectrum.py
temmeta/datatypes/misc.py
temmeta/docstrings/__init__.py
temmeta/guitools/__init__.py
temmeta/guitools/file_dialog.py
temmeta/guitools/save_file_dialog.py
temmeta/guitools/widgets.py
temmeta/roi/__init__.py
temmeta/roi/line.py
temmeta-0.0.6.dist-info/LICENSE
temmeta-0.0.6.dist-info/METADATA
temmeta-0.0.6.dist-info/WHEEL
temmeta-0.0.6.dist-info/top_level.txt
temmeta-0.0.6.dist-info/RECORD
