Metadata-Version: 2.1
Name: temmeta
Version: 0.0.6
Summary: TEMMETA is a library for transmission electron microscopy (TEM) (meta)data manipulation
Home-page: https://github.com/din14970/TEMMETA
Author: Niels Cautaerts
Author-email: nielscautaerts@hotmail.com
License: GPL-3.0
Keywords: TEM
Platform: UNKNOWN
Classifier: Topic :: Scientific/Engineering :: Physics
Classifier: Intended Audience :: Science/Research
Classifier: Operating System :: OS Independent
Classifier: Programming Language :: Python :: 3.7
Classifier: Programming Language :: Python :: 3.8
Requires-Dist: numpy
Requires-Dist: matplotlib
Requires-Dist: openpyxl
Requires-Dist: pandas
Requires-Dist: scipy
Requires-Dist: hyperspy
Requires-Dist: matplotlib-scalebar
Requires-Dist: tqdm
Requires-Dist: Pillow
